ebdtable2graph/__init__.py
ebdtable2graph/add_watermark.py
ebdtable2graph/graph_conversion.py
ebdtable2graph/graph_utils.py
ebdtable2graph/graphviz.py
ebdtable2graph/hochfrequenz-logo.svg
ebdtable2graph/kroki.py
ebdtable2graph/plantuml.py
ebdtable2graph/py.typed
ebdtable2graph/models/__init__.py
ebdtable2graph/models/ebd_graph.py
ebdtable2graph/models/ebd_table.py
ebdtable2graph/models/errors/__init__.py
ebdtable2graph-0.1.20.dist-info/LICENSE
ebdtable2graph-0.1.20.dist-info/METADATA
ebdtable2graph-0.1.20.dist-info/WHEEL
ebdtable2graph-0.1.20.dist-info/top_level.txt
ebdtable2graph-0.1.20.dist-info/RECORD
