Metadata-Version: 2.1
Name: ebdtable2graph
Version: 0.1.20
Summary: Converts (already scraped) Entscheidungsbaumdiagramm tables to real graphs
Home-page: https://github.com/Hochfrequenz/ebd_table_to_graph
Author: Hochfrequenz Unternehmensberatung GmbH
Author-email: info@hochfrequenz.de
License: mit
Project-URL: Documentation, https://github.com/Hochfrequenz/ebd_table_to_graph
Project-URL: Code, https://github.com/Hochfrequenz/ebd_table_to_graph
Project-URL: Bug tracker, https://github.com/Hochfrequenz/ebd_table_to_graph/issues
Platform: any
Classifier: Development Status :: 3 - Alpha
Classifier: Intended Audience :: Developers
Classifier: Programming Language :: Python
Classifier: Programming Language :: Python :: 3.11
Classifier: Programming Language :: Python :: 3.12
Classifier: Operating System :: OS Independent
Requires-Python: >=3.11
License-File: LICENSE
Requires-Dist: attrs
Requires-Dist: cattrs
Requires-Dist: lxml (>=4.9.3)
Requires-Dist: networkx
Requires-Dist: requests
Requires-Dist: svgutils
